Workbook

Sheet Scoring Model
A1: DatIQ — Prioritised Features Release Roadmap · Backlog Tracker
A2: Produced by a 4-member AI Model Council (Growth/Conversion · Market Strategy · Retention/UX · Platform Engineering) synthesising 6 model reports (Gemini, Perplexity, ChatGPT, Grok, DeepSeek, Meta AI) + live datiq.app review. July 16, 2026.
A4: Scoring weights (edit the blue cells — Value and Priority recalculate)
A5: CONV — Conversion-rate impact | B5: 0.22
A6: REACH — Market reach / acquisition | B6: 0.16
A7: ENG — Engagement & retention | B7: 0.2
A8: EQ — Efficiency & output quality | B8: 0.12
A9: DIFF — Differentiation | B9: 0.15
A10: MON — Monetisation fit | B10: 0.15
A11: Weights total | B11: =SUM(B5:B10) -> 1
A13: Formulas
A14: Value (0–5) = Σ(score × weight) across the six parameters
A15: Priority Index = Value × (1 + 0.05 × Council Votes) ÷ √Effort — √Effort keeps large strategic bets comparable to quick wins
A16: Council Votes = number of the 4 council members who placed the feature in their top-12 (or proposed it)
A18: All parameter scores (0–5) are averages of council-member scores where available, else chair-assigned from the source reports. Effort is in person-months (dev+design+QA).
A20: Note: Rankings guide sequencing but release assignment also honours hard dependencies (see Release Plan sheet).

Sheet Prioritised Backlog
A1: ID | B1: Feature | C1: Category | D1: Release | E1: CONV | F1: REACH | G1: ENG | H1: EQ | I1: DIFF | J1: MON | K1: Effort (pm) | L1: Council Votes | M1: Value (0–5) | N1: Priority Index | O1: Overall Rank | P1: Sources | Q1: Council Notes
A2: F01 | B2: One-click Export (CSV / JSON / Clipboard / Google Sheets) | C2: Quick Win | D2: R1 · v2.1 | E2: 5 | F2: 2 | G2: 3.3 | H2: 5 | I2: 0 | J2: 3.3 | K2: 0.4 | L2: 3 | M2: =ROUND(E2*'Scoring Model'!$B$5+F2*'Scoring Model'!$B$6+G2*'Scoring Model'!$B$7+H2*'Scoring Model'!$B$8+I2*'Scoring Model'!$B$9+J2*'Scoring Model'!$B$10,2) -> 3.18 | N2: =ROUND(M2*(1+0.05*L2)/SQRT(K2),2) -> 5.78 | O2: =RANK(N2,N$2:N$63) -> 1 | P2: Perplexity, ChatGPT, Grok, DeepSeek, Gemini | Q2: Table stakes across every competitor; #1 trial-killer today — value dies on-screen. Unanimous council support.
A3: F02 | B3: Accounts + Saved Extraction History | C3: Quick Win | D3: R1 · v2.1 | E3: 4.3 | F3: 2 | G3: 5 | H3: 3.3 | I3: 0.7 | J3: 4 | K3: 1.3 | L3: 3 | M3: =ROUND(E3*'Scoring Model'!$B$5+F3*'Scoring Model'!$B$6+G3*'Scoring Model'!$B$7+H3*'Scoring Model'!$B$8+I3*'Scoring Model'!$B$9+J3*'Scoring Model'!$B$10,2) -> 3.37 | N3: =ROUND(M3*(1+0.05*L3)/SQRT(K3),2) -> 3.4 | O3: =RANK(N3,N$2:N$63) -> 10 | P3: All 5 on-topic reports; Council A/C/D | Q3: Substrate for every later feature (collections, monitoring, API keys, teams). Free tier capped at 10 items = upgrade trigger.
A4: F07 | B4: "Extract Similar" Post-result CTA | C4: Quick Win | D4: R1 · v2.1 | E4: 3.5 | F4: 1 | G4: 4.5 | H4: 3 | I4: 2 | J4: 3.5 | K4: 0.4 | L4: 2 | M4: =ROUND(E4*'Scoring Model'!$B$5+F4*'Scoring Model'!$B$6+G4*'Scoring Model'!$B$7+H4*'Scoring Model'!$B$8+I4*'Scoring Model'!$B$9+J4*'Scoring Model'!$B$10,2) -> 3.02 | N4: =ROUND(M4*(1+0.05*L4)/SQRT(K4),2) -> 5.25 | O4: =RANK(N4,N$2:N$63) -> 2 | P4: DeepSeek (9.5/10 top pick); Council A/C | Q4: Cheapest session-depth multiplier; turns 1 extraction into 4, burns trial quota faster, hits paywall sooner.
A5: F09 | B5: AI Output Feedback Widget (thumbs up/down + comment) | C5: Quick Win | D5: R1 · v2.1 | E5: 2 | F5: 0 | G5: 3 | H5: 5 | I5: 1 | J5: 1 | K5: 0.5 | L5: 1 | M5: =ROUND(E5*'Scoring Model'!$B$5+F5*'Scoring Model'!$B$6+G5*'Scoring Model'!$B$7+H5*'Scoring Model'!$B$8+I5*'Scoring Model'!$B$9+J5*'Scoring Model'!$B$10,2) -> 1.94 | N5: =ROUND(M5*(1+0.05*L5)/SQRT(K5),2) -> 2.88 | O5: =RANK(N5,N$2:N$63) -> 16 | P5: Perplexity; Council C | Q5: Instruments perceived output quality — the silent retention variable; feeds extraction-quality improvement loop.
A6: F10 | B6: Keyboard Shortcuts / Power-user Mode | C6: Quick Win | D6: R1 · v2.1 | E6: 1 | F6: 0 | G6: 2 | H6: 2 | I6: 1 | J6: 1 | K6: 0.5 | L6: 0 | M6: =ROUND(E6*'Scoring Model'!$B$5+F6*'Scoring Model'!$B$6+G6*'Scoring Model'!$B$7+H6*'Scoring Model'!$B$8+I6*'Scoring Model'!$B$9+J6*'Scoring Model'!$B$10,2) -> 1.16 | N6: =ROUND(M6*(1+0.05*L6)/SQRT(K6),2) -> 1.64 | O6: =RANK(N6,N$2:N$63) -> 47 | P6: Perplexity | Q6: Low-cost delight for analysts and power users.
A7: F13 | B7: Transparent Pricing Page + Tier-Feature Mapping | C7: Quick Win | D7: R1 · v2.1 | E7: 4 | F7: 2.5 | G7: 0 | H7: 0 | I7: 0.5 | J7: 4.5 | K7: 0.25 | L7: 2 | M7: =ROUND(E7*'Scoring Model'!$B$5+F7*'Scoring Model'!$B$6+G7*'Scoring Model'!$B$7+H7*'Scoring Model'!$B$8+I7*'Scoring Model'!$B$9+J7*'Scoring Model'!$B$10,2) -> 2.03 | N7: =ROUND(M7*(1+0.05*L7)/SQRT(K7),2) -> 4.47 | O7: =RANK(N7,N$2:N$63) -> 3 | P7: ChatGPT, DeepSeek; Council A/B | Q7: Buyers comparison-shop ruthlessly; an uncrawlable pricing page loses deals before they start.
A8: F14 | B8: Privacy & Trust Messaging + Data-retention Statement | C8: Quick Win | D8: R1 · v2.1 | E8: 2 | F8: 1 | G8: 1 | H8: 2 | I8: 1 | J8: 3 | K8: 0.25 | L8: 1 | M8: =ROUND(E8*'Scoring Model'!$B$5+F8*'Scoring Model'!$B$6+G8*'Scoring Model'!$B$7+H8*'Scoring Model'!$B$8+I8*'Scoring Model'!$B$9+J8*'Scoring Model'!$B$10,2) -> 1.64 | N8: =ROUND(M8*(1+0.05*L8)/SQRT(K8),2) -> 3.44 | O8: =RANK(N8,N$2:N$63) -> 8 | P8: Meta AI (transferable), Council D | Q8: 'Data deleted after Xd, no training on your data' under the input box; table stakes before Agency/API deals.
A9: F15 | B9: Onboarding Tooltips / First-run Product Tour | C9: Quick Win | D9: R1 · v2.1 | E9: 3 | F9: 0 | G9: 2 | H9: 2 | I9: 0 | J9: 1 | K9: 0.5 | L9: 0 | M9: =ROUND(E9*'Scoring Model'!$B$5+F9*'Scoring Model'!$B$6+G9*'Scoring Model'!$B$7+H9*'Scoring Model'!$B$8+I9*'Scoring Model'!$B$9+J9*'Scoring Model'!$B$10,2) -> 1.45 | N9: =ROUND(M9*(1+0.05*L9)/SQRT(K9),2) -> 2.05 | O9: =RANK(N9,N$2:N$63) -> 38 | P9: Copilot (transferable), Perplexity | Q9: Clarifies the 8 extraction modes on first visit; pairs with F06 recipe chips.
A10: F50 | B10: Product Analytics + A/B Instrumentation (foundational) | C10: Platform Foundation | D10: R1 · v2.1 | E10: 1.5 | F10: 0.5 | G10: 2.5 | H10: 3.5 | I10: 0 | J10: 1.5 | K10: 0.9 | L10: 2 | M10: =ROUND(E10*'Scoring Model'!$B$5+F10*'Scoring Model'!$B$6+G10*'Scoring Model'!$B$7+H10*'Scoring Model'!$B$8+I10*'Scoring Model'!$B$9+J10*'Scoring Model'!$B$10,2) -> 1.56 | N10: =ROUND(M10*(1+0.05*L10)/SQRT(K10),2) -> 1.81 | O10: =RANK(N10,N$2:N$63) -> 44 | P10: Copilot (transferable), Council C/D | Q10: Non-negotiable: every later prioritisation claim is untestable without funnel + retention telemetry.
A11: FA3 | B11: In-product Paywall / Quota-exhaustion Upgrade Flow + Annual Plans | C11: Quick Win | D11: R1 · v2.1 | E11: 5 | F11: 0 | G11: 0 | H11: 0 | I11: 0 | J11: 5 | K11: 0.5 | L11: 1 | M11: =ROUND(E11*'Scoring Model'!$B$5+F11*'Scoring Model'!$B$6+G11*'Scoring Model'!$B$7+H11*'Scoring Model'!$B$8+I11*'Scoring Model'!$B$9+J11*'Scoring Model'!$B$10,2) -> 1.85 | N11: =ROUND(M11*(1+0.05*L11)/SQRT(K11),2) -> 2.75 | O11: =RANK(N11,N$2:N$63) -> 18 | P11: Council A (new) | Q11: Upgrade screen at the exact moment of trial exhaustion, showing which paid feature completes the current task; annual anchoring.
A12: F04 | B12: Shareable Result Permalinks + SSR ("Powered by DatIQ" loop) | C12: Growth & PLG | D12: R2 · v2.2 | E12: 4.5 | F12: 5 | G12: 3.5 | H12: 2 | I12: 3.5 | J12: 2 | K12: 1.5 | L12: 2 | M12: =ROUND(E12*'Scoring Model'!$B$5+F12*'Scoring Model'!$B$6+G12*'Scoring Model'!$B$7+H12*'Scoring Model'!$B$8+I12*'Scoring Model'!$B$9+J12*'Scoring Model'!$B$10,2) -> 3.56 | N12: =ROUND(M12*(1+0.05*L12)/SQRT(K12),2) -> 3.2 | O12: =RANK(N12,N$2:N$63) -> 13 | P12: ChatGPT (#1, 4.15), Perplexity, Meta AI; Council A/B | Q12: Every extraction becomes an indexed, shareable landing page — fixes SEO invisibility + creates the viral loop. Requires FD2 cache; ship after accounts (Council C condition) with DMCA takedown process (Council D condition).
A13: F05 | B13: Homepage Animated Demo + Example Gallery + Prompt Chips | C13: Growth & PLG | D13: R2 · v2.2 | E13: 4 | F13: 3 | G13: 1 | H13: 1 | I13: 1 | J13: 1 | K13: 0.75 | L13: 1 | M13: =ROUND(E13*'Scoring Model'!$B$5+F13*'Scoring Model'!$B$6+G13*'Scoring Model'!$B$7+H13*'Scoring Model'!$B$8+I13*'Scoring Model'!$B$9+J13*'Scoring Model'!$B$10,2) -> 1.98 | N13: =ROUND(M13*(1+0.05*L13)/SQRT(K13),2) -> 2.4 | O13: =RANK(N13,N$2:N$63) -> 30 | P13: Perplexity (#1, 43.2), Meta AI, DeepSeek | Q13: Pre-filled animated extraction on a known URL = instant aha with zero signup friction; prompt chips teach what to ask.
... A63: FB3 | B63: Lookalike Company Discovery ('find 25 similar companies') | C63: Agentic Vision | D63: R7 · v5.0+ | E63: 4 | F63: 3 | G63: 4 | H63: 4 | I63: 4 | J63: 5 | K63: 3 | L63: 1 | M63: =ROUND(E63*'Scoring Model'!$B$5+F63*'Scoring Model'!$B$6+G63*'Scoring Model'!$B$7+H63*'Scoring Model'!$B$8+I63*'Scoring Model'!$B$9+J63*'Scoring Model'!$B$10,2) -> 3.99 | N63: =ROUND(M63*(1+0.05*L63)/SQRT(K63),2) -> 2.42 | O63: =RANK(N63,N$2:N$63) -> 29 | P63: Council B (new); Clay/Ocean.io benchmark | Q63: Turns one extraction into a prospecting list; massively raises SDR willingness-to-pay.

Sheet Release Plan
A1: Release | B1: Theme | C1: Timeframe | D1: Objective | E1: # Features | F1: Total Effort (pm) | G1: Success Criteria / KPIs
A2: R1 · v2.1 | B2: Convert & Keep | C2: 0–6 weeks (Aug 2026) | D2: Stop the leaks: make value portable, persistent and purchasable. Fix activation→conversion before buying traffic. | E2: =SUMPRODUCT((LEFT('Prioritised Backlog'!$D$2:$D$63,2)=LEFT($A2,2))*1) -> 10 | F2: =ROUND(SUMPRODUCT((LEFT('Prioritised Backlog'!$D$2:$D$63,2)=LEFT($A2,2))*'Prioritised Backlog'!$K$2:$K$63),1) -> 5.5 | G2: D1 activation ≥40% (2+ extractions + 1 export); free→paid ≥3%; baseline telemetry live
A3: R2 · v2.2 | B3: Launch & Be Found | C3: 6–12 weeks (Sep–Oct 2026) | D3: Acquisition flywheel: every result a shareable indexed page; persona routes; public launch moment. | E3: =SUMPRODUCT((LEFT('Prioritised Backlog'!$D$2:$D$63,2)=LEFT($A3,2))*1) -> 8 | F3: =ROUND(SUMPRODUCT((LEFT('Prioritised Backlog'!$D$2:$D$63,2)=LEFT($A3,2))*'Prioritised Backlog'!$K$2:$K$63),1) -> 7.3 | G3: Indexed pages >50; organic visits baseline; referral K-factor >0.15; PH launch top-5 of day
A4: R3 · v3.0 | B4: Habit & Reliability | C4: Q4 2026 | D4: Turn one-shot use into weekly habit; harden the engine (JS rendering, queue, compliance) that everything else depends on. | E4: =SUMPRODUCT((LEFT('Prioritised Backlog'!$D$2:$D$63,2)=LEFT($A4,2))*1) -> 9 | F4: =ROUND(SUMPRODUCT((LEFT('Prioritised Backlog'!$D$2:$D$63,2)=LEFT($A4,2))*'Prioritised Backlog'!$K$2:$K$63),1) -> 15.7 | G4: D7 retention 2× baseline; extractions/session ≥3; monitoring beta on 500 URLs; fetch success ≥95%
A5: R4 · v3.5 | B5: Ecosystem & Developers | C5: Q1 2027 | D5: Open the platform: API, SDK, MCP, Zapier, template library; monetisation architecture (Teams tier, metered API). | E5: =SUMPRODUCT((LEFT('Prioritised Backlog'!$D$2:$D$63,2)=LEFT($A5,2))*1) -> 9 | F5: =ROUND(SUMPRODUCT((LEFT('Prioritised Backlog'!$D$2:$D$63,2)=LEFT($A5,2))*'Prioritised Backlog'!$K$2:$K$63),1) -> 11 | G5: API signups; MCP installs; Zapier listing live; WAU/MAU ≥40%; free→paid ≥5%
A6: R5 · v4.0 | B6: Intelligence & Quality | C6: Q2–Q3 2027 | D6: Differentiate on being right: self-healing, confidence scoring, verified emails, tech-stack + domain intelligence; extension distribution. | E6: =SUMPRODUCT((LEFT('Prioritised Backlog'!$D$2:$D$63,2)=LEFT($A6,2))*1) -> 9 | F6: =ROUND(SUMPRODUCT((LEFT('Prioritised Backlog'!$D$2:$D$63,2)=LEFT($A6,2))*'Prioritised Backlog'!$K$2:$K$63),1) -> 19.7 | G6: Extraction accuracy ≥97% on template set; verified-email credits revenue; extension WAU; D30 retention 2×
A7: R6 · v4.5 | B7: Teams & Enterprise | C7: Q4 2027 | D7: Multiplayer + enterprise readiness: workspaces, CRM, SOC2 (trigger-based), CI feed as vertical product. | E7: =SUMPRODUCT((LEFT('Prioritised Backlog'!$D$2:$D$63,2)=LEFT($A7,2))*1) -> 5 | F7: =ROUND(SUMPRODUCT((LEFT('Prioritised Backlog'!$D$2:$D$63,2)=LEFT($A7,2))*'Prioritised Backlog'!$K$2:$K$63),1) -> 15 | G7: Multi-seat accounts ≥15% of revenue; first enterprise deals; NRR >110%
A8: R7 · v5.0+ | B8: Agentic Vision | C8: 2028+ | D8: Category creation: autonomous research agent, chat-over-library, lookalikes, waterfall enrichment, knowledge graph. | E8: =SUMPRODUCT((LEFT('Prioritised Backlog'!$D$2:$D$63,2)=LEFT($A8,2))*1) -> 12 | F8: =ROUND(SUMPRODUCT((LEFT('Prioritised Backlog'!$D$2:$D$63,2)=LEFT($A8,2))*'Prioritised Backlog'!$K$2:$K$63),1) -> 41.5 | G8: Agent unit economics positive; library-chat WAU; ARPU expansion
A10: Effort sums use the Effort column of the Prioritised Backlog; features spanning releases (e.g. F17 beta→GA) are counted in their first release.

Sheet Council Verdicts
A1: Debate | B1: Positions | C1: Council Resolution
A2: Ship viral permalinks (F04) first vs. fix retention first | B2: Growth (A) + Market (B) wanted F04 in first release; Retention (C) objected — sharing into a stateless product amplifies churn; Engineering (D) flagged DMCA + cache dependency. | C2: RESOLVED: F04 ships in R2, immediately after accounts/history (R1) and with the FD2 result-cache and a takedown process. Viral loop lands on a product that can retain the users it acquires.
A3: Monitoring now vs. infrastructure first | B3: All four members back monitoring (F17) — the only unanimous feature. Engineering (D) insisted a monitor that silently breaks on redesigns is a churn event with a paying customer attached. | C3: RESOLVED: F17 beta in R3 on a curated domain set, GA in R4 gated on anti-bot/JS infra (F36) and retry ladder (FD1 partial). C accepted the sequencing.
A4: Developer lane (API/MCP) vs. non-developer focus | B4: Growth (A) challenged the dev play — Firecrawl owns that lane at $16/mo. Market (B) countered that MCP is distribution, not a head-on dev fight; Engineering (D) showed F23 is a thin wrapper once F21 exists. | C4: RESOLVED: API+MCP in R4 as a distribution channel with persona-flavoured tools (extract_pricing, find_contacts) rather than a raw-scraping API price war. Primary positioning stays no-code.
A5: Autonomous agent as flagship vs. science project | B5: Gemini + Perplexity reports pitched agentic crawling as the future; every council member voted DELAY/KILL for 12 months — cost 20-50x per run, compounding error rates, no reliability layer yet. | C5: RESOLVED: F34 parked in R7 (2028+), explicitly gated on F35 self-healing, F36 infra, and positive unit economics. MCP (F23) carries the 'agent-ready' narrative meanwhile.
A6: Team features now vs. teams pricing first | B6: DeepSeek + Grok pushed team workspaces early; Growth (A): with 11 teams total there is no multiplayer demand yet — 'sell seats, then build for them.' | C6: RESOLVED: Teams *pricing tier* (F42) in R4; full workspaces/RBAC (F31) in R6 after collections (F03) prove shared-work demand. Dependency chain F02→F03→F31 respected.
A7: Auth/paywalled-page extraction (F33) | B7: Gemini ranked the action sandbox high (10.0); Engineering (D) flagged CFAA/ToS/GDPR exposure and credential-vault security burden a small team cannot carry. | C7: RESOLVED: KILLED from the 18-month roadmap; revisit post-SOC2 (F41) with legal counsel only.
A8: Wrong-product source reports | B8: Copilot analysed a dating app; Meta AI analysed a spreadsheet-analysis product (datiq.netlify.app). Council screened both for transferable ideas rather than discarding. | C8: RESOLVED: Salvaged — onboarding tooltips (F15), re-engagement deep links (F49), analytics discipline (F50) from Copilot; prompt chips (F05), privacy reassurance (F14), localization (F44), micro-tool/gallery patterns from Meta AI. All product-specific recommendations (swipe mechanics, spreadsheet connectors) excluded.
